LICENSE
README.md
setup.py
DisambiguationCorpus/DisambiguatedWord.c
DisambiguationCorpus/DisambiguatedWord.pxd
DisambiguationCorpus/DisambiguatedWord.pyx
DisambiguationCorpus/DisambiguationCorpus.c
DisambiguationCorpus/DisambiguationCorpus.pxd
DisambiguationCorpus/DisambiguationCorpus.pyx
DisambiguationCorpus/__init__.py
MorphologicalAnalysis/FiniteStateMachine.c
MorphologicalAnalysis/FiniteStateMachine.pxd
MorphologicalAnalysis/FiniteStateMachine.pyx
MorphologicalAnalysis/FsmMorphologicalAnalyzer.c
MorphologicalAnalysis/FsmMorphologicalAnalyzer.pxd
MorphologicalAnalysis/FsmMorphologicalAnalyzer.pyx
MorphologicalAnalysis/FsmParse.c
MorphologicalAnalysis/FsmParse.pxd
MorphologicalAnalysis/FsmParse.pyx
MorphologicalAnalysis/FsmParseList.c
MorphologicalAnalysis/FsmParseList.pxd
MorphologicalAnalysis/FsmParseList.pyx
MorphologicalAnalysis/InflectionalGroup.c
MorphologicalAnalysis/InflectionalGroup.pxd
MorphologicalAnalysis/InflectionalGroup.pyx
MorphologicalAnalysis/MetamorphicParse.c
MorphologicalAnalysis/MetamorphicParse.pxd
MorphologicalAnalysis/MetamorphicParse.pyx
MorphologicalAnalysis/MorphologicalParse.c
MorphologicalAnalysis/MorphologicalParse.pxd
MorphologicalAnalysis/MorphologicalParse.pyx
MorphologicalAnalysis/MorphologicalTag.py
MorphologicalAnalysis/MorphotacticEngine.c
MorphologicalAnalysis/MorphotacticEngine.pxd
MorphologicalAnalysis/MorphotacticEngine.pyx
MorphologicalAnalysis/State.c
MorphologicalAnalysis/State.pxd
MorphologicalAnalysis/State.pyx
MorphologicalAnalysis/Transition.c
MorphologicalAnalysis/Transition.pxd
MorphologicalAnalysis/Transition.pyx
MorphologicalAnalysis/__init__.py
MorphologicalAnalysis/data/__init__.py
MorphologicalAnalysis/data/pronunciations.txt
MorphologicalAnalysis/data/suffixes.txt
MorphologicalAnalysis/data/turkish_finite_state_machine.xml
NlpToolkit_MorphologicalAnalysis_Cy.egg-info/PKG-INFO
NlpToolkit_MorphologicalAnalysis_Cy.egg-info/SOURCES.txt
NlpToolkit_MorphologicalAnalysis_Cy.egg-info/dependency_links.txt
NlpToolkit_MorphologicalAnalysis_Cy.egg-info/requires.txt
NlpToolkit_MorphologicalAnalysis_Cy.egg-info/top_level.txt
nlptoolkit_morphologicalanalysis_cy.egg-info/PKG-INFO
nlptoolkit_morphologicalanalysis_cy.egg-info/SOURCES.txt
nlptoolkit_morphologicalanalysis_cy.egg-info/dependency_links.txt
nlptoolkit_morphologicalanalysis_cy.egg-info/requires.txt
nlptoolkit_morphologicalanalysis_cy.egg-info/top_level.txt