Metadata-Version: 2.1
Name: nlptoolkit-morphologicalanalysis-cy
Version: 1.0.34
Summary: Turkish Morphological Analysis
Home-page: https://github.com/StarlangSoftware/TurkishMorphologicalAnalysis-Cy
Author: olcaytaner
Author-email: olcay.yildiz@ozyegin.edu.tr
License: UNKNOWN
Platform: UNKNOWN
